moldyn/__init__.py
moldyn/data/atom_preset.py
moldyn/main.py
moldyn/processing/__init__.py
moldyn/processing/data_proc.py
moldyn/processing/strain.glsl
moldyn/processing/strain_CPU.py
moldyn/processing/visualisation.py
moldyn/simulation/__init__.py
moldyn/simulation/builder.py
moldyn/simulation/forces_CPU.py
moldyn/simulation/forces_GPU.py
moldyn/simulation/runner.py
moldyn/simulation/templates/moldyn.glsl
moldyn/ui/__init__.py
moldyn/ui/_conv.py
moldyn/ui/create_model.py
moldyn/ui/define_external_forces.py
moldyn/ui/draggableLine.py
moldyn/ui/edit_model.py
moldyn/ui/mainwindow.py
moldyn/ui/model_viewer.py
moldyn/ui/qt/create_model.py
moldyn/ui/qt/create_model.ui
moldyn/ui/qt/define_external_forces.py
moldyn/ui/qt/define_external_forces.ui
moldyn/ui/qt/edit_model.py
moldyn/ui/qt/edit_model.ui
moldyn/ui/qt/mainwindow.py
moldyn/ui/qt/mainwindow.ui
moldyn/ui/qt/make.bat
moldyn/ui/qt/species_params.py
moldyn/ui/qt/species_params.ui
moldyn/ui/species_params.py
moldyn/utils/MIT.txt
moldyn/utils/__init__.py
moldyn/utils/appdirs.py
moldyn/utils/data_mng.py
moldyn/utils/datreant/AUTHORS
moldyn/utils/datreant/LICENSE
moldyn/utils/datreant/__init__.py
moldyn/utils/datreant/collections.py
moldyn/utils/datreant/core/__init__.py
moldyn/utils/datreant/exceptions.py
moldyn/utils/datreant/manipulators.py
moldyn/utils/datreant/metadata.py
moldyn/utils/datreant/names.py
moldyn/utils/datreant/rsync.py
moldyn/utils/datreant/scripts/__init__.py
moldyn/utils/datreant/scripts/datreant_07to1.py
moldyn/utils/datreant/scripts/tests/test_datreant_07to1.py
moldyn/utils/datreant/selectionparser.py
moldyn/utils/datreant/state.py
moldyn/utils/datreant/tests/__init__.py
moldyn/utils/datreant/tests/test_collections.py
moldyn/utils/datreant/tests/test_locks.py
moldyn/utils/datreant/tests/test_manipulators.py
moldyn/utils/datreant/tests/test_parser.py
moldyn/utils/datreant/tests/test_rsync.py
moldyn/utils/datreant/tests/test_treants.py
moldyn/utils/datreant/tests/test_trees.py
open_moldyn-0.1.0.dist-info/entry_points.txt
open_moldyn-0.1.0.dist-info/LICENSE
open_moldyn-0.1.0.dist-info/WHEEL
open_moldyn-0.1.0.dist-info/METADATA
open_moldyn-0.1.0.dist-info/RECORD
